hacker_dev_sdk/__init__.py
hacker_dev_sdk/command_execute.py
hacker_dev_sdk/concurrent_run.py
hacker_dev_sdk/project_path.py
hacker_dev_sdk-0.0.2.dist-info/LICENSE
hacker_dev_sdk-0.0.2.dist-info/METADATA
hacker_dev_sdk-0.0.2.dist-info/WHEEL
hacker_dev_sdk-0.0.2.dist-info/top_level.txt
hacker_dev_sdk-0.0.2.dist-info/RECORD
