Metadata-Version: 2.1
Name: hacker-dev-sdk
Version: 0.0.2
Summary: A useful, general SDK for hackers
Home-page: https://github.com/shellfeel/HackerDevSdk.git
Author: 9eek
Author-email: voodoos_hearty.0e@icloud.com
Classifier: Programming Language :: Python :: 3.8
Classifier: License :: OSI Approved :: MIT License
Classifier: Operating System :: OS Independent
License-File: LICENSE
